app/__init__.py
app/__main__.py
app/__version__.py
app/cli.py
app/enums.py
app/rich_diff.py
rich_diff-1.0.4.dist-info/METADATA
rich_diff-1.0.4.dist-info/WHEEL
rich_diff-1.0.4.dist-info/entry_points.txt
rich_diff-1.0.4.dist-info/top_level.txt
rich_diff-1.0.4.dist-info/RECORD
