Metadata-Version: 2.1
Name: rich-diff
Version: 1.0.4
Summary: CLI based diff Viewer
Home-page: https://github.com/sureshdsk/rich-diff
Author: sureshdsk
Author-email: dsk@sureshdsk.dev
License: UNKNOWN
Platform: UNKNOWN
Classifier: Programming Language :: Python :: 3.7
Requires-Dist: rich (==10.9.0)
Requires-Dist: textual (==0.1.11)
Requires-Dist: typer (==0.3.2)
